{
  "name": "Demostream",
  "contractId": "K-0N7RAK7",
  "format": "HLS",
  "cpcode": 7651234,
  "ingestAccelerated": false,
  "encoderZone": "EUROPE",
  "backupEncoderZone": "AUSTRALIA",
  "isDedicatedOrigin": false,
  "activeArchiveDurationInDays": 2,
  "groupId": 32145,
  "allowedIps": [
    "192.0.2.19"
  ],
  "additionalEmailIds": [
    "xyz@akamai1.com"
  ],
  "origin": {
    "hostName": "demo-host1"
  },
  "streamAuth": {
    "username": "hgildong",
    "password": "123abc!",
    "algorithm": "SHA512"
  }
}