[
  {
    "accountId": "A-CCT7890",
    "accountName": "Internet Company",
    "categories": [
      {
        "categoryId": "SECURITY",
        "categoryName": "Managed Security Support",
        "links": [
          {
            "rel": "self",
            "href": "/case-management/v3/categories/SECURITY?accountId=F-AC-000000"
          }
        ]
      }
    ]
  },
  {
    "accountId": "A-CCT9012",
    "accountName": "Main Street Corporation",
    "categories": [
      {
        "categoryId": "BILLING",
        "categoryName": "Billing Support Issue or Question",
        "links": [
          {
            "rel": "self",
            "href": "/case-management/v3/categories/BILLING?accountId=F-AC-000001"
          }
        ]
      },
      {
        "categoryId": "TECHNICAL",
        "categoryName": "Technical Support Issue",
        "links": [
          {
            "rel": "self",
            "href": "/case-management/v3/categories/TECHNICAL?accountId=F-AC-000001"
          }
        ]
      }
    ]
  }
]